aiovk/__init__.py
aiovk/api.py
aiovk/drivers.py
aiovk/exceptions.py
aiovk/longpoll.py
aiovk/mixins.py
aiovk/parser.py
aiovk/pools.py
aiovk/sessions.py
aiovk/shaping.py
tests/__init__.py
tests/utils.py
tests/functional/__init__.py
tests/functional/conftest.py
tests/functional/test_drivers.py
tests/functional/test_longpool.py
tests/functional/test_sessions.py
tests/unit/__init__.py
tests/unit/test_api.py
tests/unit/test_longpool.py
tests/unit/test_pools.py
tests/unit/test_shaping.py
aiovk-4.1.0.dist-info/LICENSE
aiovk-4.1.0.dist-info/METADATA
aiovk-4.1.0.dist-info/WHEEL
aiovk-4.1.0.dist-info/top_level.txt
aiovk-4.1.0.dist-info/RECORD
