Metadata-Version: 2.1
Name: aiovk
Version: 4.1.0
Summary: vk.com API python wrapper for asyncio
Home-page: https://github.com/alexanderlarin/aiovk
Author: Alexander Larin
Author-email: ekzebox@gmail.com
License: MIT License
Keywords: vk.com api vk wrappper asyncio
Classifier: Environment :: Web Environment
Classifier: Intended Audience :: Developers
Classifier: License :: OSI Approved :: MIT License
Classifier: Programming Language :: Python :: 3.6
Classifier: Programming Language :: Python :: 3.7
Classifier: Programming Language :: Python :: 3.8
Classifier: Programming Language :: Python :: 3.9
Classifier: Topic :: Software Development :: Libraries :: Python Modules
Requires-Python: >=3.6
License-File: LICENSE
Requires-Dist: aiohttp (>=3.7.3)
Requires-Dist: aiohttp-socks (>=0.5.5)
